gdey075z08_driver/__init__.py
gdey075z08_driver/driver.py
gdey075z08_driver/epdif.py
gdey075z08_driver-0.0.5.dist-info/METADATA
gdey075z08_driver-0.0.5.dist-info/WHEEL
gdey075z08_driver-0.0.5.dist-info/licenses/LICENSE
gdey075z08_driver-0.0.5.dist-info/RECORD
