Metadata-Version: 2.1
Name: gdey075z08_driver
Version: 0.0.5
Summary: Driver library to GDEY075Z08 e-paper display
Project-URL: Homepage, https://github.com/zhufucdev/gdey075z08_driver
Project-URL: Bug Tracker, https://github.com/zhufucdev/gdey075z08_driver/issues
Author-email: zhufucdev <1095291434@qq.com>
License-File: LICENSE
Classifier: License :: OSI Approved :: MIT License
Classifier: Operating System :: POSIX :: Linux
Classifier: Programming Language :: Python :: 3
Requires-Python: >=3.7
Requires-Dist: pillow>=9.4.0
Requires-Dist: rpi-gpio>=0.7.1
Requires-Dist: spidev>=3.6
